{
  "uuid": "4bbae44a-5ea9-45c2-8752-905b54380ee0",

  "name":{
    "realname": "[OST_7_NAME]",
    "known_as": ["[OST_7_KNOWN_1]", "[OST_7_KNOWN_2]"]
  },
  "desc": "[OST_7_DESC]",

  "release_date": 1612623990,
  "no": 7,
  "track_type": 0,
  "duration": 120,
  "filetype": 1,

  "composer": {
    "composer_id": 1
  },

  "used_by": {
    "other": {
      "other": []
    }
  },

  "tags": {
    "overall": ["chaos", "energetic", "naughty"],
    "beginning": [],
    "middle": [],
    "ending": []
  },

  "version": [
    {
      "url": [
        {
          "value": "https://www.youtube.com/watch?v=pEg_d2f6myw",
          "platform": 3,
          "short_desc": ""
        }
      ],
      "desc": "[OST_VERSION_ORIGINAL]",
      "is_main": true
    }
  ],

  "special_case": {
    "is_ost": true,
    "is_bond_memory": false,
    "is_story": true,
    "is_battle": false,
    "is_event": false
  },

  "reference": [],

  "image": {
    "value": "/static/images/background/BG_View_Kivotos.jpg",
    "platform": -1,
    "short_desc": ""
  }
}