{"uuid": "9a62753b-d708-4f2c-9b77-7c9a305a8588", "filetype": 15, "filetype_sub": 1, "name": "[STORY_BOND_HARUKA_3_NAME]", "desc": ["[STORY_BOND_HARUKA_3_DESC_1]"], "pos": {"student": "HARUKA", "segment": 3, "favor_rank": 5}, "image": {"platform": -1, "value": "", "short_desc": ""}, "data": {"all": {"background": ["BG_BigPlaza_Sunset.jpg", "BG_CityOffice_Night.jpg"], "character": ["Haruka"], "track": ["OST_6", "OST_30", "OST_3", "OST_44"]}, "track_to_bg": {"OST_6": ["BG_BigPlaza_Sunset.jpg"], "OST_0": ["BG_BigPlaza_Sunset.jpg", "BG_CityOffice_Night.jpg"], "OST_30": ["BG_BigPlaza_Sunset.jpg"], "OST_3": ["BG_BigPlaza_Sunset.jpg"], "OST_44": ["BG_CityOffice_Night.jpg"]}, "track_to_char": {"OST_6": ["Haruka"], "OST_3": ["Haruka"], "OST_44": ["Haruka"]}, "char_to_bg": {"Haruka": ["BG_BigPlaza_Sunset.jpg", "BG_CityOffice_Night.jpg"]}, "char_to_char": {}, "special": {"flag": false, "track": "OST_0"}}, "is_memory": false}