{"uuid": "aee49749-1be1-4d2c-8a1f-1df24f871408", "filetype": 14, "filetype_sub": 1, "name": "[STORY_EVENT_819_10_NAME]", "desc": ["[STORY_EVENT_819_10_DESC_1]"], "pos": {"event_id": 819, "segment": 10}, "image": {"platform": -1, "value": "", "short_desc": ""}, "data": {"all": {"background": ["BG_TrinityStreet2_Night.jpg"], "character": ["Tsurugi", "Hasumi", "Mine"], "track": ["OST_31", "OST_21"]}, "track_to_bg": {"OST_31": ["BG_TrinityStreet2_Night.jpg"], "OST_0": ["BG_TrinityStreet2_Night.jpg"], "OST_21": ["BG_TrinityStreet2_Night.jpg"]}, "track_to_char": {"OST_31": ["Tsurugi", "Hasumi", "Mine"], "OST_21": ["Hasumi", "Tsurugi", "Mine"]}, "char_to_bg": {"Tsurugi": ["BG_TrinityStreet2_Night.jpg"], "Hasumi": ["BG_TrinityStreet2_Night.jpg"], "Mine": ["BG_TrinityStreet2_Night.jpg"]}, "char_to_char": {}, "special": {"flag": false, "track": "OST_0"}}, "is_battle": false}