{"uuid": "9577403d-e8aa-4d3d-a36c-46bd2698e90a", "filetype": 15, "filetype_sub": 1, "name": "[STORY_BOND_NAGISA_4_NAME]", "desc": ["[STORY_BOND_NAGISA_4_DESC_1]"], "pos": {"student": "NAGISA", "segment": 4, "favor_rank": 6}, "image": {"platform": -1, "value": "", "short_desc": ""}, "data": {"all": {"background": ["BG_FamilyRestaurant.jpg", "BG_TrinityStreet.jpg"], "character": ["Nagisa"], "track": ["OST_4"]}, "track_to_bg": {"OST_4": ["BG_FamilyRestaurant.jpg", "BG_TrinityStreet.jpg"]}, "track_to_char": {"OST_4": ["Nagisa"]}, "char_to_bg": {"Nagisa": ["BG_TrinityStreet.jpg"]}, "char_to_char": {}, "special": {"flag": false, "track": "OST_0"}}, "is_memory": false}