{"uuid": "2bf52e97-0141-4a74-b48e-b95a86ad8814", "filetype": 15, "filetype_sub": 1, "name": "[STORY_BOND_SUZUMI_5_NAME]", "desc": ["[STORY_BOND_SUZUMI_5_DESC_1]"], "pos": {"student": "SUZUMI", "segment": 5, "favor_rank": 15}, "image": {"platform": -1, "value": "", "short_desc": ""}, "data": {"all": {"background": ["BG_TrinityCampus.jpg", "BG_TrinityMarket.jpg", "BG_View_Sky.jpg"], "character": ["Suzumi"], "track": ["OST_16", "OST_33", "OST_44", "OST_37"]}, "track_to_bg": {"OST_0": ["BG_TrinityCampus.jpg", "BG_TrinityMarket.jpg", "BG_View_Sky.jpg"], "OST_16": ["BG_TrinityCampus.jpg"], "OST_33": ["BG_TrinityMarket.jpg"], "OST_44": ["BG_TrinityMarket.jpg"], "OST_37": ["BG_View_Sky.jpg", "BG_TrinityMarket.jpg"]}, "track_to_char": {"OST_16": ["Suzumi"], "OST_33": ["Suzumi"], "OST_44": ["Suzumi"], "OST_37": ["Suzumi"]}, "char_to_bg": {"Suzumi": ["BG_TrinityCampus.jpg", "BG_TrinityMarket.jpg", "BG_View_Sky.jpg"]}, "char_to_char": {}, "special": {"flag": false, "track": "OST_0"}}, "is_memory": false}