{"uuid": "da8ed828-9075-4d4a-afb6-9e7c62d9414a", "filetype": 15, "filetype_sub": 1, "name": "[STORY_BOND_SHIGURE_HOTSPRING_4_NAME]", "desc": ["[STORY_BOND_SHIGURE_HOTSPRING_4_DESC_1]"], "pos": {"student": "SHIGURE_HOTSPRING", "segment": 4, "favor_rank": 6}, "image": {"platform": -1, "value": "", "short_desc": ""}, "data": {"all": {"background": ["BG_WinterRoad.jpg", "BG_Onsen2.jpg"], "character": ["Shigure_HotSpring"], "track": ["OST_99", "OST_83"]}, "track_to_bg": {"OST_0": ["BG_WinterRoad.jpg"], "OST_99": ["BG_WinterRoad.jpg", "BG_Onsen2.jpg"], "OST_83": ["BG_WinterRoad.jpg"]}, "track_to_char": {"OST_99": ["Shigure_HotSpring"], "OST_83": ["Shigure_HotSpring"]}, "char_to_bg": {"Shigure_HotSpring": ["BG_WinterRoad.jpg"]}, "char_to_char": {}, "special": {"flag": false, "track": "OST_0"}}, "is_memory": false}