{
  "uuid": "02cc8274-2b69-43f6-8cf2-91de2672da1f",
  "filetype": 15,
  "filetype_sub": 1,
  "name": "[STORY_BOND_SENA_1_NAME]",
  "desc": [
    "[STORY_BOND_SENA_1_DESC_1]"
  ],
  "pos": {
    "student": "SENA",
    "segment": 1,
    "favor_rank": 2
  },
  "image": {
    "platform": -1,
    "value": "",
    "short_desc": ""
  },
  "data": {
    "all": {
      "background": [
        "BG_DemolitionCity.jpg"
      ],
      "character": [
        "Sena"
      ],
      "track": [
        "OST_18",
        "OST_16",
        "OST_8"
      ]
    },
    "track_to_bg": {
      "OST_18": [
        "BG_DemolitionCity.jpg"
      ],
      "OST_0": [
        "BG_DemolitionCity.jpg"
      ],
      "OST_16": [
        "BG_DemolitionCity.jpg"
      ],
      "OST_8": [
        "BG_DemolitionCity.jpg"
      ]
    },
    "track_to_char": {
      "OST_18": [
        "Sena"
      ],
      "OST_16": [
        "Sena"
      ],
      "OST_8": [
        "Sena"
      ]
    },
    "char_to_bg": {
      "Sena": [
        "BG_DemolitionCity.jpg"
      ]
    },
    "char_to_char": {},
    "special": {
      "flag": false,
      "track": "OST_0",
      "char": []
    }
  },
  "is_memory": false
}