{"uuid": "644705cd-aa6c-4049-904d-28cffc379590", "filetype": 14, "filetype_sub": 1, "name": "[STORY_EVENT_815_8_NAME]", "desc": ["[STORY_EVENT_815_8_DESC_1]"], "pos": {"event_id": 815, "segment": 8}, "image": {"platform": -1, "value": "", "short_desc": ""}, "data": {"all": {"background": ["BG_VIPLounge.jpg", "BG_BeachFrontSide.jpg"], "character": ["Pina", "Kaede", "Shizuko_Swimsuit", "Mimori_Swimsuit", "Umika", "Chise_Swimsuit", "Izuna_Swimsuit"], "track": ["OST_76", "OST_3", "OST_53", "OST_6", "OST_11"]}, "track_to_bg": {"OST_76": ["BG_VIPLounge.jpg"], "OST_0": ["BG_VIPLounge.jpg"], "OST_3": ["BG_VIPLounge.jpg"], "OST_53": ["BG_VIPLounge.jpg"], "OST_6": ["BG_VIPLounge.jpg"], "OST_11": ["BG_VIPLounge.jpg", "BG_BeachFrontSide.jpg"]}, "track_to_char": {"OST_76": ["Pina", "Kaede", "Shizuko_Swimsuit", "Mimori_Swimsuit", "Umika"], "OST_3": ["Shizuko_Swimsuit", "Kaede"], "OST_53": ["Chise_Swimsuit", "Kaede", "Pina", "Shizuko_Swimsuit"], "OST_6": ["Mimori_Swimsuit", "Izuna_Swimsuit", "Shizuko_Swimsuit", "Kaede", "Pina"], "OST_11": ["Shizuko_Swimsuit", "Pina", "Kaede", "Mimori_Swimsuit"]}, "char_to_bg": {"Pina": ["BG_VIPLounge.jpg"], "Kaede": ["BG_VIPLounge.jpg"], "Shizuko_Swimsuit": ["BG_VIPLounge.jpg", "BG_BeachFrontSide.jpg"], "Mimori_Swimsuit": ["BG_VIPLounge.jpg"], "Umika": ["BG_VIPLounge.jpg"], "Chise_Swimsuit": ["BG_VIPLounge.jpg"], "Izuna_Swimsuit": ["BG_VIPLounge.jpg"]}, "char_to_char": {"Kaede": ["Pina", "Shizuko_Swimsuit", "Mimori_Swimsuit", "Chise_Swimsuit", "Izuna_Swimsuit"], "Pina": ["Kaede", "Shizuko_Swimsuit", "Mimori_Swimsuit", "Chise_Swimsuit", "Izuna_Swimsuit"], "Mimori_Swimsuit": ["Shizuko_Swimsuit", "Umika", "Pina", "Kaede", "Izuna_Swimsuit"], "Umika": ["Shizuko_Swimsuit", "Mimori_Swimsuit"], "Shizuko_Swimsuit": ["Mimori_Swimsuit", "Umika", "Pina", "Kaede", "Chise_Swimsuit", "Izuna_Swimsuit"], "Chise_Swimsuit": ["Kaede", "Pina", "Shizuko_Swimsuit"], "Izuna_Swimsuit": ["Mimori_Swimsuit", "Shizuko_Swimsuit", "Kaede", "Pina"]}, "special": {"flag": false, "track": "OST_0"}}, "is_battle": false}