{
  "uuid": "d7dcb2b3-2eb4-4085-9b2b-45b729b2b4ca",
  "filetype": 11,

  "name": "[STORY_MAIN_1_2_16_NAME]",
  "desc": "[STORY_MAIN_1_2_16_DESC]",
  "pos": {
    "volume": 1,
    "chapter": 2,
    "segment": 16
  },
  "image": {
    "platform": -1,
    "value": "",
    "short_desc": ""
  },

  "part": [
    {
      "name": "[STORY_MAIN_1_2_16_P1_NAME]",
      "desc": "[STORY_MAIN_1_2_16_P1_DESC]",
      "is_battle": false,
      "track": ["OST_70"],
      "background": ["BG_CS_RAID_01.jpg", "BG_CS_RAID_02.jpg"],
      "character": ["BlackSuit"]
    },
    {
      "name": "[STORY_MAIN_1_2_16_P2_NAME]",
      "desc": "[STORY_MAIN_1_2_16_P2_DESC]",
      "is_battle": false,
      "track": ["OST_70"],
      "background": ["BG_CS_Abydos_06.jpg"],
      "character": []
    },
    {
      "name": "[STORY_MAIN_1_2_16_P3_NAME]",
      "desc": "[STORY_MAIN_1_2_16_P3_DESC]",
      "is_battle": false,
      "track": ["OST_70"],
      "background": ["BG_CS_RAID_01.jpg", "BG_CS_RAID_02.jpg", "BG_DesertResidence_Night.jpg"],
      "character": ["BlackSuit"]
    },
    {
      "name": "[STORY_MAIN_1_2_16_P4_NAME]",
      "desc": "[STORY_MAIN_1_2_16_P4_DESC]",
      "is_battle": false,
      "track": ["OST_70"],
      "background": ["BG_CS_RAID_02.jpg", "BG_CS_RAID_01.jpg"],
      "character": ["BlackSuit"]
    },
    {
      "name": "[STORY_MAIN_1_2_16_P5_NAME]",
      "desc": "[STORY_MAIN_1_2_16_P5_DESC]",
      "is_battle": false,
      "track": ["OST_70"],
      "background": ["BG_CS_RAID_01.jpg"],
      "character": ["BlackSuit"]
    },
    {
      "name": "[STORY_MAIN_1_2_16_P6_NAME]",
      "desc": "[STORY_MAIN_1_2_16_P6_DESC]",
      "is_battle": false,
      "track": ["OST_70"],
      "background": ["BG_CS_Abydos_07.jpg", "BG_CS_RAID_02.jpg"],
      "character": ["BlackSuit"]
    },
    {
      "name": "[STORY_MAIN_1_2_16_P7_NAME]",
      "desc": "[STORY_MAIN_1_2_16_P7_DESC]",
      "is_battle": false,
      "track": ["OST_70"],
      "background": ["BG_CS_RAID_01.jpg"],
      "character": ["BlackSuit"]
    },
    {
      "name": "[STORY_MAIN_1_2_16_P8_NAME]",
      "desc": "[STORY_MAIN_1_2_16_P8_DESC]",
      "is_battle": false,
      "track": ["OST_70"],
      "background": ["BG_CS_Abydos_01.jpg", "BG_CS_RAID_02.jpg", "BG_CS_Abydos_07.jpg"],
      "character": ["BlackSuit"]
    },
    {
      "name": "[STORY_MAIN_1_2_16_P9_NAME]",
      "desc": "[STORY_MAIN_1_2_16_P9_DESC]",
      "is_battle": false,
      "track": ["OST_70"],
      "background": ["BG_UpperOffice_Night.jpg"],
      "character": ["BlackSuit"]
    },
    {
      "name": "[STORY_MAIN_1_2_16_P10_NAME]",
      "desc": "[STORY_MAIN_1_2_16_P10_NAME]",
      "is_battle": true,
      "track": ["OST_45"],
      "background": ["BG_CommitteeRoom_Night2.jpg"],
      "character": ["Shiroko", "Nonomi", "Serika", "Ayane"]
    },
    {
      "name": "[STORY_MAIN_1_2_16_P11_NAME]",
      "desc": "[STORY_MAIN_1_2_16_P11_NAME]",
      "is_battle": true,
      "track": ["OST_45"],
      "background": ["BG_CommitteeRoom_Night2.jpg"],
      "character": ["Shiroko", "Serika", "Nonomi", "Ayane"]
    }
  ],
  "is_battle": false
}