{
  "uuid": "41c4901c-92d8-4c03-93a1-16cb47ae34c3",
  "filetype": 15,
  "filetype_sub": 1,
  "name": "[STORY_BOND_CHINATSU_2_NAME]",
  "desc": [
    "[STORY_BOND_CHINATSU_2_DESC_1]"
  ],
  "pos": {
    "student": "CHINATSU",
    "segment": 2,
    "favor_rank": 3
  },
  "image": {
    "platform": -1,
    "value": "",
    "short_desc": ""
  },
  "data": {
    "all": {
      "background": [
        "BG_Arcade.jpg",
        "BG_ShoppingMall.jpg",
        "BG_Campus_Sunset.jpg"
      ],
      "character": [
        "Chinatsu"
      ],
      "track": [
        "OST_33",
        "OST_22"
      ]
    },
    "track_to_bg": {
      "OST_33": [
        "BG_Arcade.jpg",
        "BG_ShoppingMall.jpg"
      ],
      "OST_0": [
        "BG_Campus_Sunset.jpg"
      ],
      "OST_22": [
        "BG_Campus_Sunset.jpg"
      ]
    },
    "track_to_char": {
      "OST_33": [
        "Chinatsu"
      ],
      "OST_22": [
        "Chinatsu"
      ]
    },
    "char_to_bg": {
      "Chinatsu": [
        "BG_Arcade.jpg",
        "BG_ShoppingMall.jpg",
        "BG_Campus_Sunset.jpg"
      ]
    },
    "char_to_char": {},
    "special": {
      "flag": false,
      "track": "OST_0",
      "char": []
    }
  },
  "is_memory": false
}