{"uuid": "c728fa47-f947-4445-9314-a08decdf07ed", "filetype": 14, "filetype_sub": 1, "name": "[STORY_EVENT_825_9_NAME]", "desc": ["[STORY_EVENT_825_9_DESC_1]"], "pos": {"event_id": 825, "segment": 9}, "image": {"platform": -1, "value": "", "short_desc": ""}, "data": {"all": {"background": ["BG_UnderGroundAuction.jpg"], "character": ["Yuzu_Maid", "Toki_Bunny", "Aris_Maid", "Meitaro"], "track": ["OST_92", "OST_27", "OST_159"]}, "track_to_bg": {"OST_0": ["BG_UnderGroundAuction.jpg"], "OST_27": ["BG_UnderGroundAuction.jpg"], "OST_159": ["BG_UnderGroundAuction.jpg"]}, "track_to_char": {"OST_92": ["Yuzu_Maid", "Toki_Bunny", "Aris_Maid"], "OST_27": ["Meitaro", "Yuzu_Maid", "Toki_Bunny", "Aris_Maid"], "OST_159": ["Meitaro", "Toki_Bunny"]}, "char_to_bg": {"Aris_Maid": ["BG_UnderGroundAuction.jpg"], "Toki_Bunny": ["BG_UnderGroundAuction.jpg"], "Meitaro": ["BG_UnderGroundAuction.jpg"], "Yuzu_Maid": ["BG_UnderGroundAuction.jpg"]}, "char_to_char": {"Toki_Bunny": ["Yuzu_Maid", "Aris_Maid"], "Aris_Maid": ["Yuzu_Maid", "Toki_Bunny"], "Yuzu_Maid": ["Toki_Bunny", "Aris_Maid"]}, "special": {"flag": false, "track": "OST_0"}}, "is_battle": false}