{"uuid": "b89f2a14-fec2-4339-96da-2db05de464c8", "filetype": 14, "filetype_sub": 1, "name": "[STORY_EVENT_827_3_NAME]", "desc": ["[STORY_EVENT_827_3_DESC_1]"], "pos": {"event_id": 827, "segment": 3}, "image": {"platform": -1, "value": "", "short_desc": ""}, "data": {"all": {"background": ["BG_FishingVillage.jpg", "BG_SlumFront_Cloud.jpg", "BG_LightHousePier.jpg"], "character": ["Miyako_Swimsuit", "Saki_Swimsuit", "Miyu", "Miyu_Swimsuit"], "track": ["OST_134"]}, "track_to_bg": {"OST_134": ["BG_FishingVillage.jpg", "BG_SlumFront_Cloud.jpg", "BG_LightHousePier.jpg"]}, "track_to_char": {"OST_134": ["Miyako_Swimsuit", "Saki_Swimsuit", "Miyu", "Miyu_Swimsuit"]}, "char_to_bg": {"Miyako_Swimsuit": ["BG_FishingVillage.jpg"], "Saki_Swimsuit": ["BG_SlumFront_Cloud.jpg"], "Miyu": ["BG_LightHousePier.jpg"], "Miyu_Swimsuit": ["BG_LightHousePier.jpg"]}, "char_to_char": {}, "special": {"flag": false, "track": "OST_0"}}, "is_battle": false}