{"uuid": "13c0a4b3-cd4d-48c5-b4a5-1349b9276478", "filetype": 15, "filetype_sub": 1, "name": "[STORY_BOND_MOMOI_3_NAME]", "desc": ["[STORY_BOND_MOMOI_3_DESC_1]"], "pos": {"student": "MOMOI", "segment": 3, "favor_rank": 5}, "image": {"platform": -1, "value": "", "short_desc": ""}, "data": {"all": {"background": ["BG_CityOffice.jpg", "BG_Arcade.jpg", "BG_Market.jpg", "BG_FamilyRestaurant.jpg", "BG_CityOffice_Night.jpg"], "character": ["Momoi"], "track": ["OST_10", "OST_15"]}, "track_to_bg": {"OST_10": ["BG_CityOffice.jpg", "BG_Arcade.jpg", "BG_Market.jpg", "BG_FamilyRestaurant.jpg"], "OST_0": ["BG_CityOffice_Night.jpg"], "OST_15": ["BG_CityOffice_Night.jpg"]}, "track_to_char": {"OST_10": ["Momoi"], "OST_15": ["Momoi"]}, "char_to_bg": {"Momoi": ["BG_CityOffice.jpg", "BG_Arcade.jpg", "BG_Market.jpg", "BG_FamilyRestaurant.jpg", "BG_CityOffice_Night.jpg"]}, "char_to_char": {}, "special": {"flag": false, "track": "OST_0"}}, "is_memory": false}