{
  "uuid": "89ec72d5-67e2-4da6-8ad2-6d5c4536070c",
  "filetype": 14,
  "filetype_sub": 1,
  "name": "[STORY_EVENT_999_40_NAME]",
  "desc": [
    "[STORY_EVENT_999_40_DESC_1]"
  ],
  "pos": {
    "event_id": 999,
    "segment": 40
  },
  "image": {
    "platform": -1,
    "value": "",
    "short_desc": ""
  },
  "data": {
    "all": {
      "background": [
        "BG_GehennaClassRoom_Night.jpg"
      ],
      "character": [
        "Juri"
      ],
      "track": [
        "OST_15",
        "OST_38"
      ]
    },
    "track_to_bg": {
      "OST_0": [
        "BG_GehennaClassRoom_Night.jpg"
      ],
      "OST_15": [
        "BG_GehennaClassRoom_Night.jpg"
      ],
      "OST_38": [
        "BG_GehennaClassRoom_Night.jpg"
      ]
    },
    "track_to_char": {
      "OST_15": [
        "Juri"
      ],
      "OST_38": [
        "Juri"
      ]
    },
    "char_to_bg": {
      "Juri": [
        "BG_GehennaClassRoom_Night.jpg"
      ]
    },
    "char_to_char": {},
    "special": {
      "flag": false,
      "track": "OST_0",
      "char": []
    }
  },
  "is_battle": false
}