{
  "uuid": "d72a5cf9-9fc5-4808-9b9a-695c227935f4",
  "filetype": 14,
  "filetype_sub": 1,
  "name": "[STORY_EVENT_999_76_NAME]",
  "desc": [
    "[STORY_EVENT_999_76_DESC_1]"
  ],
  "pos": {
    "event_id": 999,
    "segment": 76
  },
  "image": {
    "platform": -1,
    "value": "",
    "short_desc": ""
  },
  "data": {
    "all": {
      "background": [
        "BG_RuinSchoolCorridor.jpg"
      ],
      "character": [
        "Misaki"
      ],
      "track": [
        "OST_105"
      ]
    },
    "track_to_bg": {
      "OST_105": [
        "BG_RuinSchoolCorridor.jpg"
      ]
    },
    "track_to_char": {
      "OST_105": [
        "Misaki"
      ]
    },
    "char_to_bg": {
      "Misaki": [
        "BG_RuinSchoolCorridor.jpg"
      ]
    },
    "char_to_char": {},
    "special": {
      "flag": false,
      "track": "OST_0",
      "char": []
    }
  },
  "is_battle": false
}